easyhec/__init__.py
easyhec/examples/__init__.py
easyhec/examples/real/__init__.py
easyhec/examples/real/base.py
easyhec/examples/real/paper.py
easyhec/examples/real/so100.py
easyhec/examples/real/robot_definitions/so100/LICENSE
easyhec/examples/real/robot_definitions/so100/README.md
easyhec/examples/real/robot_definitions/so100/so100.srdf
easyhec/examples/real/robot_definitions/so100/so100.urdf
easyhec/examples/real/robot_definitions/so100/meshes/Base.stl
easyhec/examples/real/robot_definitions/so100/meshes/Base.stl.convex.stl
easyhec/examples/real/robot_definitions/so100/meshes/Base_Motor.stl
easyhec/examples/real/robot_definitions/so100/meshes/Base_Motor.stl.convex.stl
easyhec/examples/real/robot_definitions/so100/meshes/Fixed_Jaw.stl
easyhec/examples/real/robot_definitions/so100/meshes/Fixed_Jaw.stl.convex.stl
easyhec/examples/real/robot_definitions/so100/meshes/Fixed_Jaw_Motor.stl
easyhec/examples/real/robot_definitions/so100/meshes/Fixed_Jaw_Motor.stl.convex.stl
easyhec/examples/real/robot_definitions/so100/meshes/Fixed_Jaw_part1.ply
easyhec/examples/real/robot_definitions/so100/meshes/Fixed_Jaw_part1.ply.convex.stl
easyhec/examples/real/robot_definitions/so100/meshes/Fixed_Jaw_part2.ply
easyhec/examples/real/robot_definitions/so100/meshes/Fixed_Jaw_part2.ply.convex.stl
easyhec/examples/real/robot_definitions/so100/meshes/Lower_Arm.stl
easyhec/examples/real/robot_definitions/so100/meshes/Lower_Arm.stl.convex.stl
easyhec/examples/real/robot_definitions/so100/meshes/Lower_Arm_Motor.stl
easyhec/examples/real/robot_definitions/so100/meshes/Lower_Arm_Motor.stl.convex.stl
easyhec/examples/real/robot_definitions/so100/meshes/Moving_Jaw.stl
easyhec/examples/real/robot_definitions/so100/meshes/Moving_Jaw.stl.convex.stl
easyhec/examples/real/robot_definitions/so100/meshes/Moving_Jaw_part1.ply
easyhec/examples/real/robot_definitions/so100/meshes/Moving_Jaw_part1.ply.convex.stl
easyhec/examples/real/robot_definitions/so100/meshes/Moving_Jaw_part2.ply
easyhec-0.1.9.dist-info/licenses/LICENSE
easyhec-0.1.9.dist-info/licenses/LICENSE-3RD-PARTY
easyhec-0.1.9.dist-info/METADATA
easyhec-0.1.9.dist-info/WHEEL
easyhec-0.1.9.dist-info/top_level.txt
easyhec-0.1.9.dist-info/RECORD
